gomate/__init__.py
gomate/version.py
gomate/applications/__init__.py
gomate/applications/rag.py
gomate/applications/rag_weibo.py
gomate/applications/rerank.py
gomate/applications/rewriter.py
gomate/modules/document/__init__.py
gomate/modules/document/base.py
gomate/modules/document/chunk.py
gomate/modules/document/common_parser.py
gomate/modules/document/docx_parser.py
gomate/modules/document/excel_parser.py
gomate/modules/document/html_parser.py
gomate/modules/document/huqie.txt
gomate/modules/document/huqie.txt.trie
gomate/modules/document/json_parser.py
gomate/modules/document/markdown_parser.py
gomate/modules/document/pdf_mineru_parser.py
gomate/modules/document/pdf_parser.py
gomate/modules/document/pdf_parser_fast.py
gomate/modules/document/ppt_parser.py
gomate/modules/document/rag_tokenizer.py
gomate/modules/document/text_parser.py
gomate/modules/document/txt_parser.py
gomate/modules/document/utils.py
gomate-0.0.14.dist-info/METADATA
gomate-0.0.14.dist-info/WHEEL
gomate-0.0.14.dist-info/top_level.txt
gomate-0.0.14.dist-info/RECORD
