Metadata-Version: 2.1
Name: gomate
Version: 0.0.14
Summary: RAG Framework within Reliable input,Trusted output
Home-page: https://github.com/gomate-community/GoMate
Author: gomate-community
Author-email: yanqiang@ict.ac.cn
Requires-Python: >=3.9
Requires-Dist: tqdm
Requires-Dist: hyperopt
Requires-Dist: h5py
Requires-Dist: coverage
Requires-Dist: codecov
Requires-Dist: pytest
Requires-Dist: pytest-cov
Requires-Dist: flake8
Requires-Dist: flake8-docstrings
Requires-Dist: pydocstyle
Requires-Dist: openai
Requires-Dist: datasets
Requires-Dist: langchain
Requires-Dist: langchain-core
Requires-Dist: langchain-text-splitters
Requires-Dist: langchain-huggingface
Requires-Dist: langchain-openai
Requires-Dist: langsmith
Requires-Dist: transformers
Requires-Dist: pandas
Requires-Dist: nltk
Requires-Dist: sentencepiece
Requires-Dist: PyPDF2
Requires-Dist: html2text
Requires-Dist: beautifulsoup4
Requires-Dist: faiss-cpu
Requires-Dist: umap-learn
Requires-Dist: sentence-transformers
Requires-Dist: threadpoolctl
Requires-Dist: PyMuPDF
Requires-Dist: hanziconv
Requires-Dist: datrie
Requires-Dist: xpinyin
Requires-Dist: python-pptx
Requires-Dist: pdfplumber
Requires-Dist: readability
Requires-Dist: html-text
Requires-Dist: python-docx
Requires-Dist: tortoise
Requires-Dist: python-magic
Requires-Dist: gradio
Requires-Dist: loguru
Requires-Dist: xgboost
Requires-Dist: bm25s
Requires-Dist: jieba
Requires-Dist: accelerate
Requires-Dist: FlagEmbedding
Requires-Dist: chardet
Requires-Dist: openpyxl
Requires-Dist: protobuf
Requires-Dist: peft
